easy_map/__init__.py
easy_map/easy_map.py
easy_map-0.3.dist-info/LICENSE
easy_map-0.3.dist-info/METADATA
easy_map-0.3.dist-info/WHEEL
easy_map-0.3.dist-info/top_level.txt
easy_map-0.3.dist-info/RECORD
